{
  "greeting": {
    "patterns": [
      "здарова",
      "привет",
      "здравствуйте"
    ],
    "responses": [
      "Приветствую сэр!",
      "Доброго времени суток сэр чем могу быть полезна?"
    ]
  },
  "stop": {
    "patterns": [
      "стоп",
      "пока",
      "уйди",
      "проваливай"
    ],
    "responses": ""
  },
  "wikipedia": {
    "patterns": [
      "найди в википедии"
    ],
    "responses": [
      "Приветствую сэр!",
      "Доброго времени суток сэр чем могу быть полезна?"
    ]
  },
  "time": {
    "patterns": [
      "время",
      "времени"
    ],
    "responses": [
      "сейчас время",
      "сейчас"
    ]
  },
  "search": {
    "patterns": [
      "найди",
      "что такое"
    ],
    "responses": [
      "ищу в интернете"
    ]
  },
  "google": {
    "patterns": [
      "google",
      "гугл"
    ],
    "responses": [
      "открываю google"
    ]
  },
  "youtube": {
    "patterns": [
      "youtube",
      "ютуб"
    ],
    "responses": [
      "открываю youtube"
    ]
  },
  "word": {
    "patterns": [
      "youtube",
      "ютуб"
    ],
    "responses": [
      "открываю youtube"
    ]
  }
}

